pato_gui/PatoGui.spec
pato_gui/__init__.py
pato_gui/__main__.py
pato_gui/about.py
pato_gui/pom.py
pato_gui/program.py
pato_gui/pyinstaller.py
pato_gui-4.0.1.dist-info/LICENSE
pato_gui-4.0.1.dist-info/METADATA
pato_gui-4.0.1.dist-info/WHEEL
pato_gui-4.0.1.dist-info/entry_points.txt
pato_gui-4.0.1.dist-info/RECORD
