Metadata-Version: 2.1
Name: pato-gui
Version: 4.0.1
Summary: Paulissoft Application Tools for Oracle (PATO) GUI.
Home-page: https://paulissoft.github.io/pato-gui
License: MIT
Keywords: packaging,poetry
Author: Gert-Jan Paulissen
Author-email: paulissoft@gmail.com
Requires-Python: >=3.8.1,<3.13
Classifier: Development Status :: 6 - Mature
Classifier: Environment :: Console
Classifier: Intended Audience :: Developers
Classifier: License :: OSI Approved :: MIT License
Classifier: Natural Language :: English
Classifier: Operating System :: OS Independent
Classifier: Programming Language :: Python :: 3
Classifier: Programming Language :: Python :: 3.9
Classifier: Programming Language :: Python :: 3.10
Classifier: Programming Language :: Python :: 3.11
Classifier: Programming Language :: Python :: 3.12
Classifier: Topic :: Software Development :: Build Tools
Classifier: Topic :: Software Development :: Libraries :: Python Modules
Classifier: Topic :: Utilities
Requires-Dist: gooey (>1.0.8)
Requires-Dist: pyinstaller (==6.1.0)
Project-URL: Repository, https://github.com/paulissoft/pato-gui
